ovos_skill_ggwave/LICENSE
ovos_skill_ggwave/MANIFEST.in
ovos_skill_ggwave/README.md
ovos_skill_ggwave/__init__.py
ovos_skill_ggwave/version.py
ovos_skill_ggwave/locale/ca-es/disable.ggwave.intent
ovos_skill_ggwave/locale/ca-es/enable.ggwave.intent
ovos_skill_ggwave/locale/ca-es/ggwave.already.disabled.dialog
ovos_skill_ggwave/locale/ca-es/ggwave.already.enabled.dialog
ovos_skill_ggwave/locale/ca-es/ggwave.disabled.dialog
ovos_skill_ggwave/locale/ca-es/ggwave.enabled.dialog
ovos_skill_ggwave/locale/da-dk/disable.ggwave.intent
ovos_skill_ggwave/locale/da-dk/enable.ggwave.intent
ovos_skill_ggwave/locale/da-dk/ggwave.already.disabled.dialog
ovos_skill_ggwave/locale/da-dk/ggwave.already.enabled.dialog
ovos_skill_ggwave/locale/da-dk/ggwave.disabled.dialog
ovos_skill_ggwave/locale/da-dk/ggwave.enabled.dialog
ovos_skill_ggwave/locale/de-de/disable.ggwave.intent
ovos_skill_ggwave/locale/de-de/enable.ggwave.intent
ovos_skill_ggwave/locale/de-de/ggwave.already.disabled.dialog
ovos_skill_ggwave/locale/de-de/ggwave.already.enabled.dialog
ovos_skill_ggwave/locale/de-de/ggwave.disabled.dialog
ovos_skill_ggwave/locale/de-de/ggwave.enabled.dialog
ovos_skill_ggwave/locale/en-us/disable.ggwave.intent
ovos_skill_ggwave/locale/en-us/enable.ggwave.intent
ovos_skill_ggwave/locale/en-us/ggwave.already.disabled.dialog
ovos_skill_ggwave/locale/en-us/ggwave.already.enabled.dialog
ovos_skill_ggwave/locale/en-us/ggwave.disabled.dialog
ovos_skill_ggwave/locale/en-us/ggwave.enabled.dialog
ovos_skill_ggwave/locale/en-us/ggwave.entity
ovos_skill_ggwave/locale/en-us/skill.json
ovos_skill_ggwave/locale/it-it/disable.ggwave.intent
ovos_skill_ggwave/locale/it-it/enable.ggwave.intent
ovos_skill_ggwave/locale/it-it/ggwave.already.disabled.dialog
ovos_skill_ggwave/locale/it-it/ggwave.already.enabled.dialog
ovos_skill_ggwave/locale/it-it/ggwave.disabled.dialog
ovos_skill_ggwave/locale/it-it/ggwave.enabled.dialog
ovos_skill_ggwave/ovos_skill_ggwave.egg-info/PKG-INFO
ovos_skill_ggwave/ovos_skill_ggwave.egg-info/SOURCES.txt
ovos_skill_ggwave/ovos_skill_ggwave.egg-info/dependency_links.txt
ovos_skill_ggwave/ovos_skill_ggwave.egg-info/entry_points.txt
ovos_skill_ggwave/ovos_skill_ggwave.egg-info/requires.txt
ovos_skill_ggwave/ovos_skill_ggwave.egg-info/top_level.txt
ovos_skill_ggwave-0.3.4.dist-info/LICENSE
ovos_skill_ggwave-0.3.4.dist-info/METADATA
ovos_skill_ggwave-0.3.4.dist-info/WHEEL
ovos_skill_ggwave-0.3.4.dist-info/entry_points.txt
ovos_skill_ggwave-0.3.4.dist-info/top_level.txt
ovos_skill_ggwave-0.3.4.dist-info/RECORD
