Metadata-Version: 2.1
Name: ovos-skill-ggwave
Version: 0.3.4
Summary: voice interface for ggwave plugin
Home-page: https://github.com/OpenVoiceOS/ovos-skill-ggwave
Author: OpenVoiceOS
Author-email: jarbasai@mailfence.com
License: Apache2.0
Keywords: ovos skill plugin
Platform: UNKNOWN
Requires-Dist: ovos-workshop<4.0.0,>=0.0.15
